acace/__init__.py
acace/core.py
acace-0.1.1.dist-info/LICENSE
acace-0.1.1.dist-info/METADATA
acace-0.1.1.dist-info/WHEEL
acace-0.1.1.dist-info/RECORD
