Metadata-Version: 2.3
Name: acace
Version: 0.1.1
Summary: Adaptive Context-Aware Content Engine (ACACE) – Main orchestrator package for optimizing token usage and preserving contextual coherence across LLM content generation workflows.
Author: ACACE Team
Author-email: team@acace.ai
Requires-Python: >=3.8,<4.0
Classifier: Programming Language :: Python :: 3
Classifier: Programming Language :: Python :: 3.8
Classifier: Programming Language :: Python :: 3.9
Classifier: Programming Language :: Python :: 3.10
Classifier: Programming Language :: Python :: 3.11
Classifier: Programming Language :: Python :: 3.12
Classifier: Programming Language :: Python :: 3.13
Requires-Dist: numpy (>=1.26.3,<2.0.0)
